
  { "fullText" : "HTML Version of this article coming soon! You can download a PDF from the PDF icon.",
    "title" : 
    [ "Conference Report. Fifth Dorushe Graduate Student Conference on Syriac Studies (Duke University, March 28-29, 2014)",
      "Hugoye: Journal of Syriac Studies" ],
    "author" : 
    [ "Walsh, Erin Galgay",
      "Fiano, Emmanuel" ],
    "idno" : "https:\/\/hugoye.bethmardutho.org\/article\/hv17n2crdorushe2014",
    "type" : "report",
    "displayTitleEnglish" : "Conference Report. Fifth Dorushe Graduate Student Conference on Syriac Studies (Duke University, March 28-29, 2014)" }