
  { "fullText" : "Princeton Theological Seminary, Ms. 19 Book of Prayers. Image of Nestorius. [1] The Fourth North American Syriac Symposium will be held in Princeton during July 9-12, 2003. Those interested in attending or presenting papers may add their names to the mailing list of the Symposium at http:\/\/www.bethmardutho.org (click on the IV Syriac Symposium link). A formal Call For Papers will be announced shortly. [2] The Symposium is hosted by Princeton Theological Seminary , Princeton University , The Institute for Advanced Study , and Beth Mardutho: The Syriac Institute . A traditional program of hymns and songs by various Churches of the Syriac tradition will take place during the conference. [3] The Symposium will include the Fourth International Forum on Syriac Computing, for which see the separate Call for Papers.",
    "title" : 
    [ "IV North American Syriac Symposium Syriac Christianity: Culture at the Crossroads",
      "Hugoye: Journal of Syriac Studies" ],
    "author" : 
    [ "Kiraz, George A." ],
    "idno" : "https:\/\/hugoye.bethmardutho.org\/article\/hv5n2fcsyrsym",
    "type" : "announcement",
    "displayTitleEnglish" : "IV North American Syriac Symposium Syriac Christianity: Culture at the Crossroads" }